[
    {
        "name":"SanDisk Extreme 128GB MicroSDXC Memory Card + SD Adapter with Performance",
        "price" : "38.99",
        "description" : "Extreme memory to optimize the performance of your action camera or drone, Operating temperature ,Its high quality video performance enables 4K UHD andFull HD video playback and recording",
        "ratings" : "4.5",
        "Images" :"https://image.made-in-china.com/43f34j00EOMtJgbdZUop/Bulk-128GB-Micro-SD-Memory-Card-Low-Price.jpg",
        "categories":"Electronics",
        "seller" : "Ebay",
        "stock":"20",
        "numOfReview" : 32,
        "reviews" : []
    },
    {
        "name":"Mi Security Camera 360° Camera 1080p",
        "price" : "30",
        "description" : "Home Surveillance Camera - 2.0 MP Sensor Resolution - 1080 Pixel Resolution - 110° Camera Angle - 360º Field of View - 85° Rotatable Lens - 3.9mm Focal Length - 10 IR LED Lights - 4x Zoom - Connectivity Wi-Fi IEEE 802.11 b / g / n 2.4 GHz - Storage Up to 32 GB Via MicroSD Card (class 10 and above storage card) - Two-way audio: built-in microphone and speaker - Supported operating system : Android 4.4 above or iOS 9.0 above - Input power 5V/1A - Dimensions: 11.8 x 8 x 8 cm - Weight 253 g - 1 year warranty",
        "ratings" : "4",
        "Images" : "https://tunisiatech.tn/4821-large_default/cameras-de-surveillance-xiaomi-mi-home-security-camera-360-1080p-prix-tunisie.jpg",
        "categories":"Electronics",
        "seller" : "khayri",
        "stock":"20",
        "numOfReview" : 31,
        "reviews" : []
    },
    {
        "name":"Iphone 8 ",
        "price" : "2000",
        "description" : "The eleventh iteration of the iPhone is called the iPhone 8. It was announced on September 12, 2017 and has the particularity of shipping iOS 11, an A11 SoC engraved in 10 nm and has 64 or 256 GB of storage.",
        "ratings" : "5",
        "Images":"https://images.frandroid.com/wp-content/uploads/2019/04/iphone-8-plus-1.png",
        "categories":"Electronics",
        "seller" : "khayri",
        "stock": "5",
        "numOfReview" : 18,
        "reviews" : []
    },
    {
        "name":"PNY GEFORCE GT 1030 2GB GAMER GRAPHICS CARD",
        "price" : "20",
        "description" : "PNY GeForce GT 1030 Gamer Graphics Card - Memory size: 2 GB - Memory type: GDDR4 - Memory interface size: 64 bits - Clock speed: 1151 MHz - Memory speed: 2.1 Gbps - Graphics card type: Nvidia GeForce GT 1030 - Maximum resolution: 4096 x 2160 - Bus support: PCI-E 3.0 x 16 - Microsoft DirectX: 12 - Number of screens: 2 - Connectors: HDMI 2.0b, DL-DVI",
        "ratings" : "4.5",
        "Images" : "https://image.made-in-china.com/43f34j00EOMtJgbdZUop/Bulk-128GB-Micro-SD-Memory-Card-Low-Price.jpg",
        "categories":"Electronics",
        "seller" : "Ebay",
        "stock":"20",
        "numOfReview" : 32,
        "reviews" : []



    }
   

]
  


    



